twitter_scraper_without_api/__init__.py
twitter_scraper_without_api/driver_initialisation.py
twitter_scraper_without_api/driver_utils.py
twitter_scraper_without_api/element_finder.py
twitter_scraper_without_api/scraping_utilities.py
twitter_scraper_without_api/twitter_scraper.py
twitter_scraper_without_api-0.0.6.dist-info/METADATA
twitter_scraper_without_api-0.0.6.dist-info/WHEEL
twitter_scraper_without_api-0.0.6.dist-info/top_level.txt
twitter_scraper_without_api-0.0.6.dist-info/RECORD
